SLBPPG/__init__.py
SLBPPG/model.py
SLBPPG/ppgfilter.py
slbppg-0.1.dist-info/METADATA
slbppg-0.1.dist-info/WHEEL
slbppg-0.1.dist-info/top_level.txt
slbppg-0.1.dist-info/RECORD
